[
    {
        "Diretor": "Jackie Droujko",
        "ID filme": 499553
    },
    {
        "Diretor": "Antonio Caggiano",
        "ID filme": 499553
    },
    {
        "Diretor": "Chris Shepherd",
        "ID filme": 499126
    },
    {
        "Diretor": "Jarrell Crump",
        "ID filme": 498800
    },
    {
        "Diretor": "Will Anderson",
        "ID filme": 497455
    },
    {
        "Diretor": "Emily Ann Hoffman",
        "ID filme": 496463
    },
    {
        "Diretor": "Ben White",
        "ID filme": 495879
    },
    {
        "Diretor": "Alex Bingham",
        "ID filme": 495879
    },
    {
        "Diretor": "Conrad Swanston",
        "ID filme": 495879
    },
    {
        "Diretor": "Daniel van Westen",
        "ID filme": 494764
    },
    {
        "Diretor": "Cameron Gough",
        "ID filme": 491921
    },
    {
        "Diretor": "Dmitry Milkin",
        "ID filme": 490105
    },
    {
        "Diretor": "Jonathan Hua Lang Lim",
        "ID filme": 489356
    },
    {
        "Diretor": "Mallory Grolleau",
        "ID filme": 487764
    },
    {
        "Diretor": "Martinus Klemet",
        "ID filme": 485676
    },
    {
        "Diretor": "Boris Seewald",
        "ID filme": 485278
    },
    {
        "Diretor": "Ben Phillips",
        "ID filme": 485243
    },
    {
        "Diretor": "Austen Payne",
        "ID filme": 481931
    },
    {
        "Diretor": "Marc Riba",
        "ID filme": 480701
    },
    {
        "Diretor": "Anna Solanas",
        "ID filme": 480701
    },
    {
        "Diretor": "Aaron Legg",
        "ID filme": 480421
    },
    {
        "Diretor": "Marion Ichard",
        "ID filme": 480023
    },
    {
        "Diretor": "Vincent Ethier",
        "ID filme": 479881
    },
    {
        "Diretor": "Zviane",
        "ID filme": 476496
    },
    {
        "Diretor": "Koji Ito",
        "ID filme": 476397
    },
    {
        "Diretor": "Anna Erlandsson",
        "ID filme": 476073
    },
    {
        "Diretor": "Maya Westlund",
        "ID filme": 476073
    },
    {
        "Diretor": "Aitor O\u00f1ederra",
        "ID filme": 473023
    },
    {
        "Diretor": "Sung-dae Kim",
        "ID filme": 472478
    },
    {
        "Diretor": "Sara Bacro",
        "ID filme": 472390
    },
    {
        "Diretor": "Camille Chandelier",
        "ID filme": 472390
    },
    {
        "Diretor": "Cl\u00e9ment Pierre",
        "ID filme": 472390
    },
    {
        "Diretor": "Vincent Plagniol",
        "ID filme": 472390
    },
    {
        "Diretor": "Alexis Renault",
        "ID filme": 472390
    },
    {
        "Diretor": "Juliana Berckmans",
        "ID filme": 472384
    },
    {
        "Diretor": "Alexis Agliata",
        "ID filme": 472384
    },
    {
        "Diretor": "Th\u00e9o Bonora",
        "ID filme": 472384
    },
    {
        "Diretor": "Arnaud Bellour",
        "ID filme": 472384
    },
    {
        "Diretor": "Thibaud Gambier",
        "ID filme": 472384
    },
    {
        "Diretor": "Romain Lavoine",
        "ID filme": 472384
    },
    {
        "Diretor": "Victor BESSE",
        "ID filme": 472378
    },
    {
        "Diretor": "S\u00e9bastien CAMRRUBI",
        "ID filme": 472378
    },
    {
        "Diretor": "Beno\u00eet MAILLET",
        "ID filme": 472378
    },
    {
        "Diretor": "Valentin Dornel",
        "ID filme": 472378
    },
    {
        "Diretor": "Philippe Moine",
        "ID filme": 472378
    },
    {
        "Diretor": "Romain Barbagli",
        "ID filme": 472371
    },
    {
        "Diretor": "Quentin Daumarie",
        "ID filme": 472371
    },
    {
        "Diretor": "Ma\u00ebl Ollivier-Henry",
        "ID filme": 472371
    },
    {
        "Diretor": "Maxime Quinton",
        "ID filme": 472371
    },
    {
        "Diretor": "Ana\u00efs Martin",
        "ID filme": 472371
    },
    {
        "Diretor": "Joris Chapelin",
        "ID filme": 472370
    },
    {
        "Diretor": "Julien Ferritto",
        "ID filme": 472370
    },
    {
        "Diretor": "R\u00e9my H\u00e9riss\u00e9",
        "ID filme": 472370
    },
    {
        "Diretor": "Rim Khayat",
        "ID filme": 472370
    },
    {
        "Diretor": "Matthieu Maillet",
        "ID filme": 472370
    },
    {
        "Diretor": "Pascaline De Santis",
        "ID filme": 472370
    },
    {
        "Diretor": "Tracy Harris",
        "ID filme": 472346
    },
    {
        "Diretor": "Robert Milne",
        "ID filme": 472330
    },
    {
        "Diretor": "Leonardo Cavaletti",
        "ID filme": 472324
    },
    {
        "Diretor": "Aur\u00e9lie Gomez",
        "ID filme": 472319
    },
    {
        "Diretor": "Guillaume Bissi\u00e8res",
        "ID filme": 472319
    },
    {
        "Diretor": "Jonathan Monaghan",
        "ID filme": 472176
    },
    {
        "Diretor": "Takuya Takahashi",
        "ID filme": 472165
    },
    {
        "Diretor": "Steve Wolfhard",
        "ID filme": 471218
    },
    {
        "Diretor": "Ryan Wicks",
        "ID filme": 470849
    },
    {
        "Diretor": "Victoria Vincent",
        "ID filme": 469154
    },
    {
        "Diretor": "Jamie H. Scrutton",
        "ID filme": 468832
    },
    {
        "Diretor": "Jen Haugan",
        "ID filme": 468828
    },
    {
        "Diretor": "Cenk K\u00f6ksal",
        "ID filme": 468782
    },
    {
        "Diretor": "\u00d6zg\u00fcl G\u00fcrb\u00fcz",
        "ID filme": 468782
    },
    {
        "Diretor": "Sarah Rackemann",
        "ID filme": 468051
    },
    {
        "Diretor": "Juba Polati",
        "ID filme": 466616
    },
    {
        "Diretor": "\u0160t\u011bp\u00e1n Etrych",
        "ID filme": 466176
    },
    {
        "Diretor": "Jan Petrak",
        "ID filme": 466176
    },
    {
        "Diretor": "Juan Rodr\u00edguez",
        "ID filme": 466173
    },
    {
        "Diretor": "Thierry Garance",
        "ID filme": 466173
    },
    {
        "Diretor": "Lee Yong-sun",
        "ID filme": 464902
    },
    {
        "Diretor": "Jamille van Wijngaarden",
        "ID filme": 463791
    },
    {
        "Diretor": "Steve Smith",
        "ID filme": 462973
    },
    {
        "Diretor": "Jerry Paper",
        "ID filme": 462973
    },
    {
        "Diretor": "Rushio Moriyama",
        "ID filme": 462410
    },
    {
        "Diretor": "Usher Morgan",
        "ID filme": 460284
    },
    {
        "Diretor": "Yang Huang",
        "ID filme": 459374
    },
    {
        "Diretor": "Grant Kolton",
        "ID filme": 458693
    },
    {
        "Diretor": "Claire Bataille",
        "ID filme": 456321
    },
    {
        "Diretor": "Victor Dulon",
        "ID filme": 456321
    },
    {
        "Diretor": "Pierre Herzig",
        "ID filme": 456321
    },
    {
        "Diretor": "Ga\u00ebl Lang",
        "ID filme": 456321
    },
    {
        "Diretor": "L\u00e9a Parker",
        "ID filme": 456321
    },
    {
        "Diretor": "Harry Chaskin",
        "ID filme": 454111
    },
    {
        "Diretor": "Dan Lippert",
        "ID filme": 454111
    },
    {
        "Diretor": "Justin Michael",
        "ID filme": 454111
    },
    {
        "Diretor": "Jayson Thiessen",
        "ID filme": 450255
    },
    {
        "Diretor": "Ishi Rudell",
        "ID filme": 450104
    },
    {
        "Diretor": "Marianne Hansen",
        "ID filme": 449025
    },
    {
        "Diretor": "Britt Raes",
        "ID filme": 446364
    },
    {
        "Diretor": "Morgan Miller",
        "ID filme": 445699
    },
    {
        "Diretor": "Dingo Janny",
        "ID filme": 445435
    },
    {
        "Diretor": "Sylvain Amblard",
        "ID filme": 443069
    },
    {
        "Diretor": "Alexandre Belmudes",
        "ID filme": 443069
    }
]